{
    "values": [
        {
            "value": "country1",
            "label": "Country 1",
            "visible": true,
            "default": false,
            "initial": false
        },
        {
            "value": "country2",
            "label": "Country 2",
            "visible": true,
            "default": false,
            "initial": false
        },
        {
            "value": "country3",
            "label": "Country 3",
            "visible": true,
            "default": false,
            "initial": false
        },
        {
            "value": "country4",
            "label": "Country 4",
            "visible": true,
            "default": false,
            "initial": false
        },
        {
            "value": "country5",
            "label": "Country 5",
            "visible": true,
            "default": false,
            "initial": false
        },
        {
            "value": "country6",
            "label": "Country 6",
            "visible": true,
            "default": false,
            "initial": false
        },
        {
            "value": "country7",
            "label": "Country 7",
            "visible": true,
            "default": false,
            "initial": false
        },
        {
            "value": "country8",
            "label": "Country 8",
            "visible": true,
            "default": false,
            "initial": false
        },
        {
            "value": "country9",
            "label": "Country 9",
            "visible": true,
            "default": false,
            "initial": false
        },
        {
            "value": "country10",
            "label": "Country 10",
            "visible": true,
            "default": false,
            "initial": false
        },
        {
            "value": "country11",
            "label": "Country 11",
            "visible": true,
            "default": false,
            "initial": false
        },
        {
            "value": "country12",
            "label": "Country 12",
            "visible": true,
            "default": false,
            "initial": false
        },
        {
            "value": "country13",
            "label": "Country 13",
            "visible": true,
            "default": false,
            "initial": false
        },
        {
            "value": "country14",
            "label": "Country 14",
            "visible": true,
            "default": false,
            "initial": false
        },
        {
            "value": "country15",
            "label": "Country 15",
            "visible": true,
            "default": false,
            "initial": false
        },
        {
            "value": "country16",
            "label": "Country 16",
            "visible": true,
            "default": false,
            "initial": false
        },
        {
            "value": "country17",
            "label": "Country 17",
            "visible": true,
            "default": false,
            "initial": false
        },
        {
            "value": "country18",
            "label": "Country 18",
            "visible": true,
            "default": false,
            "initial": false
        },
        {
            "value": "country19",
            "label": "Country 19",
            "visible": true,
            "default": false,
            "initial": false
        },
        {
            "value": "country20",
            "label": "Country 20",
            "visible": true,
            "default": false,
            "initial": false
        },
        {
            "value": "country21",
            "label": "Country 21",
            "visible": true,
            "default": false,
            "initial": false
        },
        {
            "value": "country22",
            "label": "Country 22",
            "visible": true,
            "default": false,
            "initial": false
        },
        {
            "value": "country23",
            "label": "Country 23",
            "visible": true,
            "default": false,
            "initial": false
        },
        {
            "value": "country24",
            "label": "Country 24",
            "visible": true,
            "default": false,
            "initial": false
        },
        {
            "value": "country25",
            "label": "Country 25",
            "visible": true,
            "default": false,
            "initial": false
        },
        {
            "value": "country26",
            "label": "Country 26",
            "visible": true,
            "default": false,
            "initial": false
        },
        {
            "value": "country27",
            "label": "Country 27",
            "visible": true,
            "default": false,
            "initial": false
        },
        {
            "value": "country28",
            "label": "Country 28",
            "visible": true,
            "default": false,
            "initial": false
        },
        {
            "value": "country29",
            "label": "Country 29",
            "visible": true,
            "default": false,
            "initial": false
        },
        {
            "value": "country30",
            "label": "Country 30",
            "visible": true,
            "default": false,
            "initial": false
        },
        {
            "value": "country31",
            "label": "Country 31",
            "visible": true,
            "default": false,
            "initial": false
        }
    ],
    "sets": [
        {
            "id": "region1",
            "values": [
                "country1",
                "country2",
                "country3"
            ]
        },
        {
            "id": "region2",
            "values": [
                "country4",
                "country5",
                "country6"
            ]
        },
        {
            "id": "region3",
            "values": [
                "country7",
                "country8",
                "country9"
            ]
        },
        {
            "id": "region4",
            "values": [
                "country10",
                "country11",
                "country12"
            ]
        },
        {
            "id": "region5",
            "values": [
                "country13",
                "country14",
                "country15"
            ]
        },
        {
            "id": "region6",
            "values": [
                "country16",
                "country17",
                "country18"
            ]
        },
        {
            "id": "region7",
            "values": [
                "country19",
                "country20",
                "country21"
            ]
        },
        {
            "id": "region8",
            "values": [
                "country22",
                "country23",
                "country24"
            ]
        },
        {
            "id": "region9",
            "values": [
                "country25",
                "country26",
                "country27",
                "country28",
                "country29",
                "country30",
                "country31"
            ]
        }
    ],
    "multi": true
}